syjson/__init__.py
syjson-2.1.6.dist-info/LICENSE
syjson-2.1.6.dist-info/METADATA
syjson-2.1.6.dist-info/WHEEL
syjson-2.1.6.dist-info/top_level.txt
syjson-2.1.6.dist-info/RECORD
