Metadata-Version: 2.1
Name: syjson
Version: 2.1.6
Summary: A library for manage jsons files as dicts
Home-page: https://github.com/DomySh/syjson
Author: DomySh
Author-email: me@domysh.com
Classifier: Programming Language :: Python :: 3
Classifier: License :: OSI Approved :: MIT License
Classifier: Operating System :: OS Independent
Requires-Python: >=3.6
License-File: LICENSE
Requires-Dist: orjson
